bhousing_model/VERSION
bhousing_model/__init__.py
bhousing_model/config.yml
bhousing_model/pipeline.py
bhousing_model/predict.py
bhousing_model/train_pipeline.py
bhousing_model/config/__init__.py
bhousing_model/config/core.py
bhousing_model/datasets/bhousing.csv
bhousing_model/processing/__init__.py
bhousing_model/processing/data_manager.py
bhousing_model/processing/validation.py
bhousing_model/trained_models/bhousing_model_output_v0.0.1.pkl
bhousing_model/trained_models/bhousing_model_output_v0.0.2.pkl
bhousing_model/trained_models/bhousing_model_output_v0.0.3.pkl
bhousing_model/trained_models/bhousing_model_output_v0.0.5.pkl
bhousing_model/trained_models/bhousing_model_output_v0.0.6.pkl
bhousing_model-0.0.6.dist-info/METADATA
bhousing_model-0.0.6.dist-info/WHEEL
bhousing_model-0.0.6.dist-info/top_level.txt
bhousing_model-0.0.6.dist-info/RECORD
